[
  {
    "title": "When Algorithms Encounter Contractual Mistakes: Insights from Frattone",
    "brief": "As contracting becomes increasingly automated, the potential for algorithmic errors raises significant legal questions.",
    "url": "https://justice-ai.hashnode.dev/when-algorithms-encounter-contractual-mistakes-insights-from-frattone",
    "publishedAt": "2026-06-11T04:25:27Z"
  },
  {
    "title": "Algorithmic Errors and the Legal Doctrine of Mistake",
    "brief": "Navigating Automated Contractual Failures Algorithmic execution introduces unique tensions when automated systems produce contracts based on incorrect assumptions or erroneous pricing.",
    "url": "https://justice-ai.hashnode.dev/algorithmic-errors-and-the-legal-doctrine-of-mistake",
    "publishedAt": "2026-06-09T07:55:43Z"
  },
  {
    "title": "Legal Frameworks for Automated Contracting",
    "brief": "Evaluating Autonomy in Algorithmic Agreements The rise of automated contracting presents a fundamental challenge to traditional legal concepts of agency and intent.",
    "url": "https://justice-ai.hashnode.dev/legal-frameworks-for-automated-contracting",
    "publishedAt": "2026-05-11T19:44:39Z"
  }
]
